README.md
pyproject.toml
setup.py
pyperch/__init__.py
pyperch/builder.py
pyperch.egg-info/PKG-INFO
pyperch.egg-info/SOURCES.txt
pyperch.egg-info/dependency_links.txt
pyperch.egg-info/requires.txt
pyperch.egg-info/top_level.txt
pyperch/config/__init__.py
pyperch/config/schema.py
pyperch/core/__init__.py
pyperch/core/callbacks.py
pyperch/core/engine.py
pyperch/core/metrics.py
pyperch/core/trainer.py
pyperch/models/__init__.py
pyperch/models/mlp.py
pyperch/optim/__init__.py
pyperch/optim/ga.py
pyperch/optim/interface.py
pyperch/optim/rhc.py
pyperch/optim/sa.py
pyperch/search/__init__.py
pyperch/search/adapter.py
pyperch/search/builder.py
pyperch/search/factory.py
pyperch/search/optuna_search.py
pyperch/search/strategy.py
pyperch/utils/__init__.py
pyperch/utils/data.py
pyperch/utils/freeze.py
pyperch/utils/plots.py
pyperch/utils/seed.py
pyperch/utils/test.py
tests/__init__.py
tests/test_freezing_trainer.py
tests/test_integration_features.py
tests/test_optuna_search_smoke.py
tests/test_perch_learns.py
tests/test_plotting_smoke.py
tests/test_reproducibility.py