Metadata-Version: 2.1
Name: pyperch
Version: 0.2.2
Summary: pyperch refactor
Home-page: https://github.com/jlm429/pyperch
Author: John Mansfield
Author-email: jlm429@gmail.com
License: MIT
Platform: Any
Classifier: Programming Language :: Python :: 3
Classifier: Programming Language :: Python :: 3.10
Classifier: Programming Language :: Python :: 3.11
Classifier: Programming Language :: Python :: 3.12
Classifier: License :: OSI Approved :: MIT License
Classifier: Operating System :: OS Independent
Requires-Python: >=3.10
Provides-Extra: dev
